RTL/Counter.v
/*
    Author: Moaz Mohamed 
    Description: Verilog code describing an n-bit counter
*/

module Counter #(
    parameter N= 4
) (
    input wire counter_rst, counter_en, clk,
    output reg [N-1:0] count
);

/*Combinational output*/
reg [N-1:0]count_comb;

always @(*) begin
    if (counter_en)
    begin
        count_comb = count + 4'b0001;
    end
    else
    begin
        count_comb = count;
    end
end

/*Sequential output*/
always @(posedge clk or negedge counter_rst) begin
    if(!counter_rst)
    begin
        count<=4'b0000;
    end
    else
    begin
        count<=count_comb;
    end
end 
endmodule

Tests/SPI/SPI_Slave.v
/*
    Author: Moaz Mohamed 
    Description: Verilog code describing the logic of the SPI slave.
*/
`include "Counter.v"
`include "Data_Memory.v"
module SPI_Slave (
    input wire MOSI,SS_n,tx_valid, rst_n, clk,
    input wire [7:0] tx_data,
    output reg MISO,rx_valid,
    output reg [9:0] rx_data
);

/*System States*/
localparam IDLE = 3'b000,
           CHK_CMD = 3'b001,
           WRITE = 3'b010,
           READ_ADDR = 3'b011,
           READ_DATA = 3'b100;           

/*Temporary signals to store the combinational output for each signal*/
reg rx_valid_next;
reg [9:0] rx_data_next;

/*State Registers*/
reg [2:0]current_state,Next_state;

/*Reading and writing enable signals*/
reg rd_en,send_en;

/*A flag to state whether the address has been read in the prev state or not*/
reg raddr_done,raddr_done_next;

/*A flag to state the data has been successfully received form the RAM*/
reg rdata_done,rdata_done_next;

/*Resgister to hold the data received from the RAM*/
reg [7:0] rdata_reg, rdata_next;

/*Shift registers used to receive the data the addresses, and the commands*/
reg [9:0] sh_reg;

/*Internal signals to control the counter & receive its output*/
reg counter_rst,counter_en;
wire [3:0] count;

/*Counter instance*/
Counter C1 (
    .clk(clk),
    .counter_rst(counter_rst),
    .counter_en(counter_en),
    .count(count)
);

/***********************State Transition******************/
always @(posedge clk, negedge rst_n) begin
    if(!rst_n)
    begin
        current_state<= IDLE;
    end
    else
    begin
        current_state <= Next_state;
    end   
end

/******************Output Assignments*********************/
always @(posedge clk, negedge rst_n) begin
    if(!rst_n)
    begin
        rx_data<='b0;
        rx_valid<='b0;
        raddr_done<='b0;
        rdata_done<='b0;
        rdata_reg<='b0;
    end
    else
    begin
        rx_data<=rx_data_next;
        rx_valid<=rx_valid_next;
        raddr_done<=raddr_done_next;
        rdata_done<=rdata_done_next;
        rdata_reg<=rdata_next;
    end
end

/***********************Next State Logic***************/
always @(*) begin
    Next_state = IDLE;
    raddr_done_next = raddr_done;

    case (current_state)
        IDLE:begin
            if(!SS_n)
            begin
                Next_state = CHK_CMD;    
            end
            else
            begin
                Next_state = IDLE;
            end
        end 
        CHK_CMD: begin
            if(SS_n)
            begin
                Next_state = IDLE;
            end
            else
            begin
                /*If MOSI == 1 && raddr_done == 1 --> The operation is READ and the memory has received the read address*/
                if(MOSI && raddr_done)
                begin
                    Next_state = READ_DATA;
                end
                /*If MOSI == 1 && raddr_done == 0 --> The operation is READ and the memory hasn't yet received the read address*/
                else if(MOSI && !raddr_done)
                begin
                    Next_state = READ_ADDR;
                end
                /*Else if MOSI == 0 --> The operation is WRITE*/
                else
                begin
                    Next_state = WRITE;
                end
            end
        end
        READ_ADDR:begin
            /*Set the read address flag to indicate that the memory has received the read address*/
            raddr_done_next = 'b1;

            if(SS_n)
            begin
                Next_state = IDLE;
            end
            else
            begin
                Next_state = READ_ADDR;
            end
        end
        READ_DATA:begin
            raddr_done_next = 'b0;
            if(SS_n)
            begin
                Next_state = IDLE;
            end
            else
            begin
                Next_state = READ_DATA;
            end
        end
        WRITE:begin
            if(SS_n)
            begin
                Next_state = IDLE;
            end
            else
            begin
                Next_state = WRITE;
            end
        end
        default:begin
            /*Keep the values as is*/
            Next_state = IDLE;
            raddr_done_next = raddr_done;
        end
    endcase
end

/***********************Output Logic*********************/
always @(*) begin
    /*Default Values*/

    /*Counter*/
    counter_rst='b1;
    counter_en='b0;

    /*Enabling signals*/
    rd_en='b0;
    send_en='b0;

    /*Register values*/
    rdata_done_next = rdata_done;
    rdata_next = rdata_reg;
    rx_data_next = rx_data;
    rx_valid_next = rx_valid;

    case (current_state)
        IDLE: begin
            /*Assign all output signals to be zero*/
            rx_data_next='b0;
            rx_valid_next='b0;

            /*Reset the counter and disable the count enable signal*/
            counter_rst='b0;
            counter_en='b0;
        end 
        CHK_CMD:begin
            /*Assign all output signals to be zero*/
            rx_data_next='b0;
            rx_valid_next='b0;
            
            /*Reset the counter and disable the count enable signal*/
            counter_rst='b0;
            counter_en='b0;
        end
        READ_ADDR:begin
            /*Check if the count has reached 10, .i.e, 10 cycles have passed*/
            if(count == 'd10)
            begin
                /*Cease receiving the data from MOSI port*/
                rd_en = 'b0;

                /*Send the data to the RAM*/
                rx_valid_next = 'b1;
                rx_data_next = sh_reg;

                /*Stop the counter, but don't reset because it's needed to retain its value*/
                counter_en='b0;
                counter_rst='b1;
            end
            else
            begin
                /*Enable the counter*/
                counter_rst = 'b1;
                counter_en = 'b1;

                /*Disable the rx_valid signal*/
                rx_valid_next = 'b0;
                rx_data_next = rx_data;

                /*Keep receiving the data from the MOSI port*/
                rd_en = 'b1;
            end
        end
        READ_DATA: begin
            /*Poll on the tx_valid signal. When it's high, receive the data sent from memory*/
            if(tx_valid && !rdata_done)
            begin
                /*Reset the counter*/
                counter_rst='b0;
                counter_en='b0;
                
                /*Set the rdata flag*/
                rdata_done_next = 'b1;

                /*Hold in the received data*/
                rdata_next = tx_data;
            end
            else
            begin
                /*Keep the value stored in the received data register*/
                rdata_next = rdata_reg;

                if(rdata_done)
                begin
                    /*Enable the counter*/
                    counter_rst='b1;
                    counter_en='b1;

                    /*Wait 8 clock cycles so that all 8-bit data have been sent*/
                    if(count == 'd8)
                    begin
                        /*Stop the counter*/
                        counter_en='b0;

                        /*Reset the data flag*/
                        rdata_done_next = 'b0;

                        /*Stop sending the data*/
                        send_en='b0;
                    end
                    else
                    begin
                        /*Keep sending the data on the MISO port*/
                        send_en = 'b1;

                        /*Keep the data flag set*/
                        rdata_done_next = 'b1;

                        /*Keep the counter enabled*/
                        counter_en='b1;
                        counter_rst='b1;
                    end
                end
                else /*Receive the dummy data to get the RAM Read Command*/
                begin
                     /*Check if the count has reached 10, .i.e, 10 cycles have passed*/
                    if(count == 'd10)
                    begin
                        /*Cease receiving the data from MOSI port*/
                        rd_en = 'b0;

                        /*Send the data to the RAM*/
                        rx_valid_next = 'b1;
                        rx_data_next = sh_reg;

                        /*Stop the counter, but don't reset because it's needed to retain its value*/
                        counter_en='b0;
                        counter_rst='b1;
                    end
                    else
                    begin
                        /*Enable the counter*/
                        counter_rst = 'b1;
                        counter_en = 'b1;

                        /*Disable the rx_valid signal*/
                        rx_valid_next = 'b0;
                        rx_data_next = rx_data;

                        /*Keep receiving the data from the MOSI port*/
                        rd_en = 'b1;
                    end
                end
            end
        end
        WRITE:begin
            /*Check if the count has reached 10, .i.e, 10 cycles have passed*/
            if(count == 'd10)
            begin
                /*Cease receiving the data from MOSI port*/
                rd_en = 'b0;

                /*Send the data to the RAM*/
                rx_valid_next = 'b1;
                rx_data_next = sh_reg;

                /*Stop the counter, but don't reset because it's needed to retain its value*/
                counter_en='b0;
                counter_rst='b1;
            end
            else
            begin
                /*Enable the counter*/
                counter_rst = 'b1;
                counter_en = 'b1;

                /*Disable the rx_valid signal*/
                rx_valid_next = 'b0;
                rx_data_next = rx_data;

                /*Keep receiving the data from the MOSI port*/
                rd_en = 'b1;
            end
        end
        default:begin
            /*Counter*/
            counter_rst='b1;
            counter_en='b0;

            /*Enabling signals*/
            rd_en='b0;
            send_en='b0;

            /*Register values*/
            rdata_done_next = rdata_done;
            rdata_next = rdata_reg;
            rx_data_next = rx_data;
            rx_valid_next = rx_valid;
        end
    endcase
end

/*************************Receiving Data Logic*****************************/
always @(posedge clk) begin
    if(rd_en)
    begin
        sh_reg <= {MOSI,sh_reg[9:1]};
    end
    else
    begin
        sh_reg <= sh_reg;
    end
end

/**************************Sending data on MISO Port Logic************************/
always @(posedge clk) begin
   if(send_en)
   begin
        MISO <= rdata_reg[count];
   end
   else
   begin
        MISO<='b0;
   end
end
endmodule

Tests/SPI/Data_Memory.v
/*
    Author: Moaz Mohamed 
    Description: Verilog code describing a 2-single-port synchronous RAM.
*/

module Data_Memory #(parameter MEM_DEPTH = 256, DATA_SIZE = 8, ADDR_SIZE = 8)
(
    input wire [9:0] din,
    input wire rx_valid,
    input wire clk,
    input wire rst_n,
    output reg [7:0] dout,
    output reg tx_valid
);

/*Create the memory array*/
reg [DATA_SIZE - 1 : 0] RAM [0 : 2**ADDR_SIZE - 1];

/*Write enable signal that is used to write data in RAM*/
reg wr_en;

/*Define registers to hold the write address & read address*/
reg [7:0]write_add_reg, write_add_next, read_add_reg, read_add_next;

/*Define register to hold the data output from the RAM*/
reg [7:0] RAM_next;

/*Define memory index*/
integer index;

always @(posedge clk , negedge rst_n) begin
    if(!rst_n)
    begin
        for (index = 0 ; index< MEM_DEPTH; index=index+1 ) begin
            RAM[index]<=8'b0000_0000;
        end
        write_add_reg <= 8'b0000_0000;
        read_add_reg <= 8'b0000_0000;
    end
    else
    begin
        if(wr_en)
        begin
            RAM[write_add_reg]<= RAM_next;
        end
        write_add_reg <= write_add_next;
        read_add_reg <= read_add_next;
    end
end   

/*Next State & Output logic*/
always @(*) begin
    write_add_next = write_add_reg;
    read_add_next = read_add_reg;
    wr_en = 1'b0;
    RAM_next = 'b0;
    tx_valid = 1'b0;
    case (din[9:8])
            2'b00: begin //save write address
                if(rx_valid)
                begin
                    write_add_next = din[7:0];
                end
                else
                begin
                    write_add_next = write_add_reg;
                end
            end
            2'b01: begin //write data into the saved write address
                if(rx_valid)
                begin
                    RAM_next = din[7:0];
                    wr_en = 1'b1;
                end
                else
                begin
                    wr_en = 1'b0;
                    RAM_next = 'b0;
                end
            end
            2'b10: begin //save read address
                if (rx_valid)
                begin
                    read_add_next = din[7:0];
                end
                else
                begin
                    read_add_next = read_add_reg; 
                end
            end
            2'b11: begin //read from the saved read address
                    tx_valid = 1'b1;
            end
            default: begin
                write_add_next = write_add_reg;
                read_add_next = read_add_reg;
                wr_en = 1'b0;
                RAM_next = 'b0;
                tx_valid = 1'b0;
            end
        endcase
end

/*Assign the output bus to hold the data stored at the read address all the time*/
always @(*) begin
    dout = RAM[read_add_reg];
end
endmodule

Tests/SPI/SPI.v
/*
    Author: Moaz Moahamed 
    Description: SPI Top Module
*/
`include "SPI_Slave.v"
`include "Data_Memory.v"

module SPI (
    input wire MOSI,SS_n,clk,rst_n,
    output wire MISO
);

/*Intermediate Signals*/
wire [9:0]rx_data;
wire rx_valid;
wire [7:0]tx_data;
wire tx_valid;

/*Inner modules instances*/

/*Data memory instance*/
Data_Memory D1 (
    .clk(clk),
    .rst_n(rst_n),
    .rx_valid(rx_valid),
    .tx_valid(tx_valid),
    .dout(tx_data),
    .din(rx_data)
);

/*SPI Slave*/
SPI_Slave S1(
    .clk(clk),
    .rst_n(rst_n),
    .MOSI(MOSI),
    .MISO(MISO),
    .SS_n(SS_n),
    .rx_data(rx_data),
    .tx_data(tx_data),
    .rx_valid(rx_valid),
    .tx_valid(tx_valid)
);
    
endmodule

Tests/SPI/SPI_tb.v
`timescale 1ns/1ps


module  SPI_tb();

/////////////////////////////////////////////////////////
///////////////////// Parameters ////////////////////////
/////////////////////////////////////////////////////////

parameter Clock_PERIOD = 10;
parameter Test_Cases = 5;

/////////////////////////////////////////////////////////
//////////////////// DUT Signals ////////////////////////
/////////////////////////////////////////////////////////

reg rst_n_tb;
reg clk_tb;
reg MOSI_tb;
reg SS_n_tb;
wire MISO_tb;

/////////////////////////////////////////////////////////
//////////////////////// Variables //////////////////////
/////////////////////////////////////////////////////////

integer index1;
integer index2;
/////////////////////////////////////////////////////////
/////////////////////// Memories ////////////////////////
/////////////////////////////////////////////////////////

reg [12:0] Test [0:3];
reg [12:0] Data_sent;
reg [7:0] Data_received;

////////////////////////////////////////////////////////
////////////////// initial block /////////////////////// 
////////////////////////////////////////////////////////

initial 
 begin
 
 // System Functions
 $dumpfile("SPI.vcd") ;       
 $dumpvars; 
 
 //Read input File
 $readmemb("Input.txt",Test);

 // initialization
 initialize();
 
 // Test Cases
 Reset();


 for(index1=0 ; index1<4; index1=index1+1)
 begin
    Data_sent=Test[index1];
    Send(Data_sent);
 end
 #(Clock_PERIOD*9)
 SS_n_tb = 1'b1;
 #100
 $stop;

 end

////////////////////////////////////////////////////////
/////////////////////// TASKS //////////////////////////
////////////////////////////////////////////////////////

/////////////// Signals Initialization //////////////////

task initialize ;
 begin
   clk_tb='b0;
   rst_n_tb='b1;
   MOSI_tb='b0;
   SS_n_tb='b1;
 end
endtask

///////////////////////// RESET /////////////////////////

task Reset;
begin
    @(negedge clk_tb) 
    rst_n_tb='b0;
    #(Clock_PERIOD)
    rst_n_tb='b1;
end
endtask

////////////////// Test Operations ////////////////////

task Send;
input [12:0] Data;
begin
    #(Clock_PERIOD)
    SS_n_tb = Data[0];
    for(index2=1; index2<12;index2=index2+1)
    begin
        #(Clock_PERIOD)
        MOSI_tb = Data[index2];
    end
    #(Clock_PERIOD)
    SS_n_tb=Data[12];
end
endtask

////////////////// Check Out Response  ////////////////////


////////////////////////////////////////////////////////
////////////////// Clock Generator  ////////////////////
////////////////////////////////////////////////////////

always #(Clock_PERIOD/2) clk_tb=~clk_tb;

////////////////////////////////////////////////////////
/////////////////// DUT Instantation ///////////////////
////////////////////////////////////////////////////////

SPI S1 (
    .clk(clk_tb),
    .rst_n(rst_n_tb),
    .MOSI(MOSI_tb),
    .MISO(MISO_tb),
    .SS_n(SS_n_tb)
);
endmodule

Tests/SPI/SPI.vcd
$date
	Thu Aug 10 03:26:51 2023
$end
$version
	ModelSim Version 10.5
$end
$timescale
	1ps
$end

$scope module SPI_tb $end
$var parameter 32 ! Clock_PERIOD $end
$var parameter 32 " Test_Cases $end
$var reg 1 # rst_n_tb $end
$var reg 1 $ clk_tb $end
$var reg 1 % MOSI_tb $end
$var reg 1 & SS_n_tb $end
$var wire 1 ' MISO_tb $end
$var integer 32 ( index1 $end
$var integer 32 ) index2 $end
$var reg 13 * Data_sent [12:0] $end
$var reg 8 + Data_received [7:0] $end

$scope task initialize $end
$upscope $end

$scope task Reset $end
$upscope $end

$scope task Send $end
$var reg 13 , Data [12:0] $end
$upscope $end

$scope module S1 $end
$var wire 1 - MOSI $end
$var wire 1 . SS_n $end
$var wire 1 / clk $end
$var wire 1 0 rst_n $end
$var wire 1 ' MISO $end
$var wire 1 1 rx_data [9] $end
$var wire 1 2 rx_data [8] $end
$var wire 1 3 rx_data [7] $end
$var wire 1 4 rx_data [6] $end
$var wire 1 5 rx_data [5] $end
$var wire 1 6 rx_data [4] $end
$var wire 1 7 rx_data [3] $end
$var wire 1 8 rx_data [2] $end
$var wire 1 9 rx_data [1] $end
$var wire 1 : rx_data [0] $end
$var wire 1 ; rx_valid $end
$var wire 1 < tx_data [7] $end
$var wire 1 = tx_data [6] $end
$var wire 1 > tx_data [5] $end
$var wire 1 ? tx_data [4] $end
$var wire 1 @ tx_data [3] $end
$var wire 1 A tx_data [2] $end
$var wire 1 B tx_data [1] $end
$var wire 1 C tx_data [0] $end
$var wire 1 D tx_valid $end

$scope module D1 $end
$var parameter 32 E MEM_DEPTH $end
$var parameter 32 F DATA_SIZE $end
$var parameter 32 G ADDR_SIZE $end
$var wire 1 1 din [9] $end
$var wire 1 2 din [8] $end
$var wire 1 3 din [7] $end
$var wire 1 4 din [6] $end
$var wire 1 5 din [5] $end
$var wire 1 6 din [4] $end
$var wire 1 7 din [3] $end
$var wire 1 8 din [2] $end
$var wire 1 9 din [1] $end
$var wire 1 : din [0] $end
$var wire 1 ; rx_valid $end
$var wire 1 / clk $end
$var wire 1 0 rst_n $end
$var reg 8 H dout [7:0] $end
$var reg 1 I tx_valid $end
$var reg 1 J wr_en $end
$var reg 8 K write_add_reg [7:0] $end
$var reg 8 L write_add_next [7:0] $end
$var reg 8 M read_add_reg [7:0] $end
$var reg 8 N read_add_next [7:0] $end
$var reg 8 O RAM_next [7:0] $end
$var integer 32 P index $end
$upscope $end

$scope module S1 $end
$var parameter 3 Q IDLE $end
$var parameter 3 R CHK_CMD $end
$var parameter 3 S WRITE $end
$var parameter 3 T READ_ADDR $end
$var parameter 3 U READ_DATA $end
$var wire 1 - MOSI $end
$var wire 1 . SS_n $end
$var wire 1 D tx_valid $end
$var wire 1 0 rst_n $end
$var wire 1 / clk $end
$var wire 1 < tx_data [7] $end
$var wire 1 = tx_data [6] $end
$var wire 1 > tx_data [5] $end
$var wire 1 ? tx_data [4] $end
$var wire 1 @ tx_data [3] $end
$var wire 1 A tx_data [2] $end
$var wire 1 B tx_data [1] $end
$var wire 1 C tx_data [0] $end
$var reg 1 V MISO $end
$var reg 1 W rx_valid $end
$var reg 10 X rx_data [9:0] $end
$var reg 1 Y rx_valid_next $end
$var reg 10 Z rx_data_next [9:0] $end
$var reg 3 [ current_state [2:0] $end
$var reg 3 \ Next_state [2:0] $end
$var reg 1 ] rd_en $end
$var reg 1 ^ send_en $end
$var reg 1 _ raddr_done $end
$var reg 1 ` raddr_done_next $end
$var reg 1 a rdata_done $end
$var reg 1 b rdata_done_next $end
$var reg 8 c rdata_reg [7:0] $end
$var reg 8 d rdata_next [7:0] $end
$var reg 10 e sh_reg [9:0] $end
$var reg 1 f counter_rst $end
$var reg 1 g counter_en $end
$var wire 1 h count [3] $end
$var wire 1 i count [2] $end
$var wire 1 j count [1] $end
$var wire 1 k count [0] $end

$scope module C1 $end
$var parameter 32 l N $end
$var wire 1 m counter_rst $end
$var wire 1 n counter_en $end
$var wire 1 / clk $end
$var reg 4 o count [3:0] $end
$var reg 4 p count_comb [3:0] $end
$upscope $end
$upscope $end
$upscope $end
$upscope $end
$enddefinitions $end
#0
$dumpvars
1#
0$
0%
1&
bx *
bx +
bx ,
bx H
xI
xJ
bx K
bx L
bx M
bx N
bx O
xV
xW
bx X
xY
bx Z
bx [
b0 \
x]
x^
x_
x`
xa
xb
bx c
bx d
bx e
xf
xg
bx o
bx p
b1010 !
b101 "
b100000000 E
b1000 F
b1000 G
b0 Q
b1 R
b10 S
b11 T
b100 U
b100 l
bx (
bx )
bx P
x'
x:
x9
x8
x7
x6
x5
x4
x3
x2
x1
x;
xC
xB
xA
x@
x?
x>
x=
x<
xD
xk
xj
xi
xh
10
0/
1.
0-
xn
xm
$end
#5000
1$
1/
b0 [
0V
0'
1f
0g
0]
0^
b0 Z
0Y
0f
0m
0n
b0 o
0k
0j
0i
0h
1f
bx Z
xY
b0 Z
0Y
0f
b0 p
#10000
0$
0/
0#
00
b0 P
b1 P
b10 P
b11 P
b100 P
b101 P
b110 P
b111 P
b1000 P
b1001 P
b1010 P
b1011 P
b1100 P
b1101 P
b1110 P
b1111 P
b10000 P
b10001 P
b10010 P
b10011 P
b10100 P
b10101 P
b10110 P
b10111 P
b11000 P
b11001 P
b11010 P
b11011 P
b11100 P
b11101 P
b11110 P
b11111 P
b100000 P
b100001 P
b100010 P
b100011 P
b100100 P
b100101 P
b100110 P
b100111 P
b101000 P
b101001 P
b101010 P
b101011 P
b101100 P
b101101 P
b101110 P
b101111 P
b110000 P
b110001 P
b110010 P
b110011 P
b110100 P
b110101 P
b110110 P
b110111 P
b111000 P
b111001 P
b111010 P
b111011 P
b111100 P
b111101 P
b111110 P
b111111 P
b1000000 P
b1000001 P
b1000010 P
b1000011 P
b1000100 P
b1000101 P
b1000110 P
b1000111 P
b1001000 P
b1001001 P
b1001010 P
b1001011 P
b1001100 P
b1001101 P
b1001110 P
b1001111 P
b1010000 P
b1010001 P
b1010010 P
b1010011 P
b1010100 P
b1010101 P
b1010110 P
b1010111 P
b1011000 P
b1011001 P
b1011010 P
b1011011 P
b1011100 P
b1011101 P
b1011110 P
b1011111 P
b1100000 P
b1100001 P
b1100010 P
b1100011 P
b1100100 P
b1100101 P
b1100110 P
b1100111 P
b1101000 P
b1101001 P
b1101010 P
b1101011 P
b1101100 P
b1101101 P
b1101110 P
b1101111 P
b1110000 P
b1110001 P
b1110010 P
b1110011 P
b1110100 P
b1110101 P
b1110110 P
b1110111 P
b1111000 P
b1111001 P
b1111010 P
b1111011 P
b1111100 P
b1111101 P
b1111110 P
b1111111 P
b10000000 P
b10000001 P
b10000010 P
b10000011 P
b10000100 P
b10000101 P
b10000110 P
b10000111 P
b10001000 P
b10001001 P
b10001010 P
b10001011 P
b10001100 P
b10001101 P
b10001110 P
b10001111 P
b10010000 P
b10010001 P
b10010010 P
b10010011 P
b10010100 P
b10010101 P
b10010110 P
b10010111 P
b10011000 P
b10011001 P
b10011010 P
b10011011 P
b10011100 P
b10011101 P
b10011110 P
b10011111 P
b10100000 P
b10100001 P
b10100010 P
b10100011 P
b10100100 P
b10100101 P
b10100110 P
b10100111 P
b10101000 P
b10101001 P
b10101010 P
b10101011 P
b10101100 P
b10101101 P
b10101110 P
b10101111 P
b10110000 P
b10110001 P
b10110010 P
b10110011 P
b10110100 P
b10110101 P
b10110110 P
b10110111 P
b10111000 P
b10111001 P
b10111010 P
b10111011 P
b10111100 P
b10111101 P
b10111110 P
b10111111 P
b11000000 P
b11000001 P
b11000010 P
b11000011 P
b11000100 P
b11000101 P
b11000110 P
b11000111 P
b11001000 P
b11001001 P
b11001010 P
b11001011 P
b11001100 P
b11001101 P
b11001110 P
b11001111 P
b11010000 P
b11010001 P
b11010010 P
b11010011 P
b11010100 P
b11010101 P
b11010110 P
b11010111 P
b11011000 P
b11011001 P
b11011010 P
b11011011 P
b11011100 P
b11011101 P
b11011110 P
b11011111 P
b11100000 P
b11100001 P
b11100010 P
b11100011 P
b11100100 P
b11100101 P
b11100110 P
b11100111 P
b11101000 P
b11101001 P
b11101010 P
b11101011 P
b11101100 P
b11101101 P
b11101110 P
b11101111 P
b11110000 P
b11110001 P
b11110010 P
b11110011 P
b11110100 P
b11110101 P
b11110110 P
b11110111 P
b11111000 P
b11111001 P
b11111010 P
b11111011 P
b11111100 P
b11111101 P
b11111110 P
b11111111 P
b100000000 P
b0 K
b0 M
b0 X
0W
0_
0a
b0 c
0:
09
08
07
06
05
04
03
02
01
0;
0`
1f
0b
b0 d
0f
b0 L
b0 N
0J
b0 O
0I
b0 H
0D
0C
0B
0A
0@
0?
0>
0=
0<
1f
0f
#15000
1$
1/
b0 P
b1 P
b10 P
b11 P
b100 P
b101 P
b110 P
b111 P
b1000 P
b1001 P
b1010 P
b1011 P
b1100 P
b1101 P
b1110 P
b1111 P
b10000 P
b10001 P
b10010 P
b10011 P
b10100 P
b10101 P
b10110 P
b10111 P
b11000 P
b11001 P
b11010 P
b11011 P
b11100 P
b11101 P
b11110 P
b11111 P
b100000 P
b100001 P
b100010 P
b100011 P
b100100 P
b100101 P
b100110 P
b100111 P
b101000 P
b101001 P
b101010 P
b101011 P
b101100 P
b101101 P
b101110 P
b101111 P
b110000 P
b110001 P
b110010 P
b110011 P
b110100 P
b110101 P
b110110 P
b110111 P
b111000 P
b111001 P
b111010 P
b111011 P
b111100 P
b111101 P
b111110 P
b111111 P
b1000000 P
b1000001 P
b1000010 P
b1000011 P
b1000100 P
b1000101 P
b1000110 P
b1000111 P
b1001000 P
b1001001 P
b1001010 P
b1001011 P
b1001100 P
b1001101 P
b1001110 P
b1001111 P
b1010000 P
b1010001 P
b1010010 P
b1010011 P
b1010100 P
b1010101 P
b1010110 P
b1010111 P
b1011000 P
b1011001 P
b1011010 P
b1011011 P
b1011100 P
b1011101 P
b1011110 P
b1011111 P
b1100000 P
b1100001 P
b1100010 P
b1100011 P
b1100100 P
b1100101 P
b1100110 P
b1100111 P
b1101000 P
b1101001 P
b1101010 P
b1101011 P
b1101100 P
b1101101 P
b1101110 P
b1101111 P
b1110000 P
b1110001 P
b1110010 P
b1110011 P
b1110100 P
b1110101 P
b1110110 P
b1110111 P
b1111000 P
b1111001 P
b1111010 P
b1111011 P
b1111100 P
b1111101 P
b1111110 P
b1111111 P
b10000000 P
b10000001 P
b10000010 P
b10000011 P
b10000100 P
b10000101 P
b10000110 P
b10000111 P
b10001000 P
b10001001 P
b10001010 P
b10001011 P
b10001100 P
b10001101 P
b10001110 P
b10001111 P
b10010000 P
b10010001 P
b10010010 P
b10010011 P
b10010100 P
b10010101 P
b10010110 P
b10010111 P
b10011000 P
b10011001 P
b10011010 P
b10011011 P
b10011100 P
b10011101 P
b10011110 P
b10011111 P
b10100000 P
b10100001 P
b10100010 P
b10100011 P
b10100100 P
b10100101 P
b10100110 P
b10100111 P
b10101000 P
b10101001 P
b10101010 P
b10101011 P
b10101100 P
b10101101 P
b10101110 P
b10101111 P
b10110000 P
b10110001 P
b10110010 P
b10110011 P
b10110100 P
b10110101 P
b10110110 P
b10110111 P
b10111000 P
b10111001 P
b10111010 P
b10111011 P
b10111100 P
b10111101 P
b10111110 P
b10111111 P
b11000000 P
b11000001 P
b11000010 P
b11000011 P
b11000100 P
b11000101 P
b11000110 P
b11000111 P
b11001000 P
b11001001 P
b11001010 P
b11001011 P
b11001100 P
b11001101 P
b11001110 P
b11001111 P
b11010000 P
b11010001 P
b11010010 P
b11010011 P
b11010100 P
b11010101 P
b11010110 P
b11010111 P
b11011000 P
b11011001 P
b11011010 P
b11011011 P
b11011100 P
b11011101 P
b11011110 P
b11011111 P
b11100000 P
b11100001 P
b11100010 P
b11100011 P
b11100100 P
b11100101 P
b11100110 P
b11100111 P
b11101000 P
b11101001 P
b11101010 P
b11101011 P
b11101100 P
b11101101 P
b11101110 P
b11101111 P
b11110000 P
b11110001 P
b11110010 P
b11110011 P
b11110100 P
b11110101 P
b11110110 P
b11110111 P
b11111000 P
b11111001 P
b11111010 P
b11111011 P
b11111100 P
b11111101 P
b11111110 P
b11111111 P
b100000000 P
#20000
1#
b0 (
b1000000001000 *
b1000000001000 ,
0$
10
0/
#25000
1$
1/
#30000
0&
b1 )
0$
0.
0/
b1 \
#35000
1$
1/
b1 [
b0 \
b10 \
1f
0f
#40000
b10 )
0$
0/
#45000
1$
1/
b10 [
b0 \
b10 \
1f
1g
1]
1m
1n
b1 p
#50000
b11 )
0$
0/
#55000
1$
1/
b1 o
b0xxxxxxxxx e
1k
0g
0]
1g
1]
b10 p
#60000
1%
b100 )
0$
1-
0/
b0 \
b10 \
#65000
1$
1/
b10xxxxxxxx e
b10 o
0k
1j
b11 p
0g
0]
1g
1]
#70000
0%
b101 )
0$
0-
0/
b0 \
b10 \
#75000
1$
1/
b11 o
b10xxxxxxx e
1k
0g
0]
1g
1]
b100 p
#80000
b110 )
0$
0/
#85000
1$
1/
b10xxxxxx e
b100 o
0k
0j
1i
b101 p
0g
0]
1g
1]
#90000
b111 )
0$
0/
#95000
1$
1/
b101 o
b10xxxxx e
1k
0g
0]
1g
1]
b110 p
#100000
b1000 )
0$
0/
#105000
1$
1/
b10xxxx e
b110 o
0k
1j
b111 p
0g
0]
1g
1]
#110000
b1001 )
0$
0/
#115000
1$
1/
b111 o
b10xxx e
1k
0g
0]
1g
1]
b1000 p
#120000
b1010 )
0$
0/
#125000
1$
1/
b10xx e
b1000 o
0k
0j
0i
1h
b1001 p
0g
0]
1g
1]
#130000
b1011 )
0$
0/
#135000
1$
1/
b1001 o
b10x e
1k
0g
0]
1g
1]
b1010 p
#140000
b1100 )
0$
0/
#145000
1$
1/
b10 e
b1010 o
0k
1j
b1011 p
0g
0]
1Y
b10 Z
0n
b1010 p
#150000
1&
b1 (
b1011111111100 *
b1011111111100 ,
0$
1.
0/
b0 \
#155000
1$
1/
b0 [
b10 X
1W
19
1;
b10 L
b0 Z
0Y
0f
0m
b0 o
0j
0h
1f
b10 Z
1Y
b0 Z
0Y
0f
b0 p
#160000
0&
b1 )
0$
0.
0/
b1 \
#165000
1$
1/
b10 K
b0 X
0W
b1 [
09
0;
b0 \
b10 \
1f
0f
#170000
b10 )
0$
0/
#175000
1$
1/
b10 [
b0 \
b10 \
1f
1g
1]
1m
1n
b1 p
#180000
1%
b11 )
0$
1-
0/
b0 \
b10 \
#185000
1$
1/
b1 o
b1000000001 e
1k
0g
0]
1g
1]
b10 p
#190000
b100 )
0$
0/
#195000
1$
1/
b1100000000 e
b10 o
0k
1j
b11 p
0g
0]
1g
1]
#200000
b101 )
0$
0/
#205000
1$
1/
b11 o
b1110000000 e
1k
0g
0]
1g
1]
b100 p
#210000
b110 )
0$
0/
#215000
1$
1/
b1111000000 e
b100 o
0k
0j
1i
b101 p
0g
0]
1g
1]
#220000
b111 )
0$
0/
#225000
1$
1/
b101 o
b1111100000 e
1k
0g
0]
1g
1]
b110 p
#230000
b1000 )
0$
0/
#235000
1$
1/
b1111110000 e
b110 o
0k
1j
b111 p
0g
0]
1g
1]
#240000
b1001 )
0$
0/
#245000
1$
1/
b111 o
b1111111000 e
1k
0g
0]
1g
1]
b1000 p
#250000
b1010 )
0$
0/
#255000
1$
1/
b1111111100 e
b1000 o
0k
0j
0i
1h
b1001 p
0g
0]
1g
1]
#260000
b1011 )
0$
0/
#265000
1$
1/
b1001 o
b1111111110 e
1k
0g
0]
1g
1]
b1010 p
#270000
0%
b1100 )
0$
0-
0/
b0 \
b10 \
#275000
1$
1/
b111111111 e
b1010 o
0k
1j
b1011 p
0g
0]
1Y
b111111111 Z
0n
b1010 p
#280000
1&
b10 (
b1100000001010 *
b1100000001010 ,
0$
1.
0/
b0 \
#285000
1$
1/
b0 [
b111111111 X
1W
1:
19
18
17
16
15
14
13
12
1;
b11111111 O
1J
b0 Z
0Y
0f
0m
b0 o
0j
0h
1f
b111111111 Z
1Y
b0 Z
0Y
0f
b0 p
#290000
0&
b1 )
0$
0.
0/
b1 \
