RTL/Data_Memory.v
/*
    Author: Moaz Mohamed 
    Description: Verilog code describing a 2-single-port synchronous RAM.
*/

module RAM_2Port #(parameter MEM_DEPTH = 256, DATA_SIZE = 8, ADDR_SIZE = 8)
(
    input wire [9:0] din,
    input wire rx_valid,
    input wire clk,
    input wire rst_n,
    output reg [7:0] dout,
    output wire tx_valid
);

/*Create the memory array*/
reg [DATA_SIZE - 1 : 0] RAM [0 : 2**ADDR_SIZE - 1];

/*Define registers to hold the write address & read address*/
reg [7:0]write_add, read_add;

/*Define memory index*/
integer index;

always @(posedge clk , negedge rst_n) begin
    if(!rst_n)
    begin
        for (index = 0 ; index< MEM_DEPTH; index=index+1 ) begin
            RAM[index]<=8'b0000_0000;
        end
        write_add <= 8'b0000_0000;
        read_add <= 8'b0000_0000;
    end
    else
    begin
        case (din[9:8])
            2'b00: if(rx_valid)begin
                write_add <= din[7:0];
            end
            2'b01: RAM[write_add] <= din[7:0];
            2'b10: if (rx_valid) begin
                read_add <= din[7:0];
            end
            2'b11: begin
                if (tx_valid) begin
                    dout <= RAM[read_add];
                end
            end
        endcase
    end
end

/*Assign tx_valid to be high whenever the command is read,.i.e, din[9] = 1*/
assign tx_valid = din[9];
    
endmodule

RTL/Data_Memory_tb.v
/*
    Author: Moaz Mohamed 
    Description: Testbench for the 2-single-port synchronous RAM.
*/

`timescale 1ns/100ps

module RAM_2Port_tb ();

reg [9:0] din_tb;
reg rx_valid_tb;
reg clk_tb;
reg rst_n_tb;
wire [7:0] dout_tb;
wire tx_valid_tb;

/*
    Test cases to be covered:
    1) Memory initialized to zero after reset
    2) write address is saved when din[9:8] = 2'b00 & rx_valid is high.
    3) din[7:0] is written in the specified write address, but in the next clock cycle.
    4) If tx_valid is high --> read operation.
    5) During read operation, if din[8] == 0 --> Keep the read address = din[7:0].
    6) When din[8] == 1 --> output data stored at the read address location in memory on the dout bus. But in the next clk cycle.
*/

/*Module instance*/
RAM_2Port DUT (
    .din(din_tb),
    .rx_valid(rx_valid_tb),
    .clk(clk_tb),
    .rst_n(rst_n_tb),
    .dout(dout_tb),
    .tx_valid(tx_valid_tb)
);

/*Clock Generation with 10ns period*/
always #5 clk_tb=~clk_tb;

/*Initial block*/
initial begin
    $dumpfile("Data_mem.vcd");
    $dumpvars;

    /*Initial values*/
    clk_tb=1'b0;
    rx_valid_tb=1'b0;
    rst_n_tb=1'b1;
    din_tb=10'b00_0000_1010;

    /*Test case 1: Reset*/
    #10
    $display("Test Case 1: Reset");
    rst_n_tb=1'b0;
    #5
    rst_n_tb=1'b1;

    /*Test case 2: save write address after setting rx_valid to high*/
    $display("Test Case 2: Save write address");
    #5
    rx_valid_tb=1'b1;
    #10

    /*Test case 3: write data in specified memory location*/
    rx_valid_tb=1'b0;
    din_tb=10'b01_0000_1011;
    #10

    /*Test case 4: save read address if rx_valid and tx-valid are set*/
    rx_valid_tb=1'b1;
    din_tb=10'b10_0000_1010;
    #10
    rx_valid_tb=1'b0;
    din_tb[9:8]=2'b11;
    #10
    $stop;

end
endmodule

Modelsim/Data_mem.vcd
$date
	Wed Jul 19 09:04:15 2023
$end
$version
	ModelSim Version 10.5
$end
$timescale
	100ps
$end

$scope module RAM_2Port_tb $end
$var reg 10 ! din_tb [9:0] $end
$var reg 1 " rx_valid_tb $end
$var reg 1 # clk_tb $end
$var reg 1 $ rst_n_tb $end
$var wire 1 % dout_tb [7] $end
$var wire 1 & dout_tb [6] $end
$var wire 1 ' dout_tb [5] $end
$var wire 1 ( dout_tb [4] $end
$var wire 1 ) dout_tb [3] $end
$var wire 1 * dout_tb [2] $end
$var wire 1 + dout_tb [1] $end
$var wire 1 , dout_tb [0] $end
$var wire 1 - tx_valid_tb $end

$scope module DUT $end
$var parameter 32 . MEM_DEPTH $end
$var parameter 32 / DATA_SIZE $end
$var parameter 32 0 ADDR_SIZE $end
$var wire 1 1 din [9] $end
$var wire 1 2 din [8] $end
$var wire 1 3 din [7] $end
$var wire 1 4 din [6] $end
$var wire 1 5 din [5] $end
$var wire 1 6 din [4] $end
$var wire 1 7 din [3] $end
$var wire 1 8 din [2] $end
$var wire 1 9 din [1] $end
$var wire 1 : din [0] $end
$var wire 1 ; rx_valid $end
$var wire 1 < clk $end
$var wire 1 = rst_n $end
$var reg 8 > dout [7:0] $end
$var wire 1 - tx_valid $end
$var reg 8 ? write_add [7:0] $end
$var reg 8 @ read_add [7:0] $end
$var integer 32 A index $end
$upscope $end
$upscope $end
$enddefinitions $end
#0
$dumpvars
b1010 !
0"
0#
1$
bx >
bx ?
bx @
b100000000 .
b1000 /
b1000 0
bx A
x,
x+
x*
x)
x(
x'
x&
x%
0-
1=
0<
0;
0:
19
08
17
06
05
04
03
02
01
$end
#50
1#
1<
#100
0$
0#
0=
0<
b0 A
b1 A
b10 A
b11 A
b100 A
b101 A
b110 A
b111 A
b1000 A
b1001 A
b1010 A
b1011 A
b1100 A
b1101 A
b1110 A
b1111 A
b10000 A
b10001 A
b10010 A
b10011 A
b10100 A
b10101 A
b10110 A
b10111 A
b11000 A
b11001 A
b11010 A
b11011 A
b11100 A
b11101 A
b11110 A
b11111 A
b100000 A
b100001 A
b100010 A
b100011 A
b100100 A
b100101 A
b100110 A
b100111 A
b101000 A
b101001 A
b101010 A
b101011 A
b101100 A
b101101 A
b101110 A
b101111 A
b110000 A
b110001 A
b110010 A
b110011 A
b110100 A
b110101 A
b110110 A
b110111 A
b111000 A
b111001 A
b111010 A
b111011 A
b111100 A
b111101 A
b111110 A
b111111 A
b1000000 A
b1000001 A
b1000010 A
b1000011 A
b1000100 A
b1000101 A
b1000110 A
b1000111 A
b1001000 A
b1001001 A
b1001010 A
b1001011 A
b1001100 A
b1001101 A
b1001110 A
b1001111 A
b1010000 A
b1010001 A
b1010010 A
b1010011 A
b1010100 A
b1010101 A
b1010110 A
b1010111 A
b1011000 A
b1011001 A
b1011010 A
b1011011 A
b1011100 A
b1011101 A
b1011110 A
b1011111 A
b1100000 A
b1100001 A
b1100010 A
b1100011 A
b1100100 A
b1100101 A
b1100110 A
b1100111 A
b1101000 A
b1101001 A
b1101010 A
b1101011 A
b1101100 A
b1101101 A
b1101110 A
b1101111 A
b1110000 A
b1110001 A
b1110010 A
b1110011 A
b1110100 A
b1110101 A
b1110110 A
b1110111 A
b1111000 A
b1111001 A
b1111010 A
b1111011 A
b1111100 A
b1111101 A
b1111110 A
b1111111 A
b10000000 A
b10000001 A
b10000010 A
b10000011 A
b10000100 A
b10000101 A
b10000110 A
b10000111 A
b10001000 A
b10001001 A
b10001010 A
b10001011 A
b10001100 A
b10001101 A
b10001110 A
b10001111 A
b10010000 A
b10010001 A
b10010010 A
b10010011 A
b10010100 A
b10010101 A
b10010110 A
b10010111 A
b10011000 A
b10011001 A
b10011010 A
b10011011 A
b10011100 A
b10011101 A
b10011110 A
b10011111 A
b10100000 A
b10100001 A
b10100010 A
b10100011 A
b10100100 A
b10100101 A
b10100110 A
b10100111 A
b10101000 A
b10101001 A
b10101010 A
b10101011 A
b10101100 A
b10101101 A
b10101110 A
b10101111 A
b10110000 A
b10110001 A
b10110010 A
b10110011 A
b10110100 A
b10110101 A
b10110110 A
b10110111 A
b10111000 A
b10111001 A
b10111010 A
b10111011 A
b10111100 A
b10111101 A
b10111110 A
b10111111 A
b11000000 A
b11000001 A
b11000010 A
b11000011 A
b11000100 A
b11000101 A
b11000110 A
b11000111 A
b11001000 A
b11001001 A
b11001010 A
b11001011 A
b11001100 A
b11001101 A
b11001110 A
b11001111 A
b11010000 A
b11010001 A
b11010010 A
b11010011 A
b11010100 A
b11010101 A
b11010110 A
b11010111 A
b11011000 A
b11011001 A
b11011010 A
b11011011 A
b11011100 A
b11011101 A
b11011110 A
b11011111 A
b11100000 A
b11100001 A
b11100010 A
b11100011 A
b11100100 A
b11100101 A
b11100110 A
b11100111 A
b11101000 A
b11101001 A
b11101010 A
b11101011 A
b11101100 A
b11101101 A
b11101110 A
b11101111 A
b11110000 A
b11110001 A
b11110010 A
b11110011 A
b11110100 A
b11110101 A
b11110110 A
b11110111 A
b11111000 A
b11111001 A
b11111010 A
b11111011 A
b11111100 A
b11111101 A
b11111110 A
b11111111 A
b100000000 A
b0 ?
b0 @
#150
1$
1#
1=
1<
#200
1"
0#
1;
0<
#250
1#
1<
b1010 ?
#300
0"
b100001011 !
0#
0;
1:
12
0<
#350
1#
1<
#400
1"
b1000001010 !
0#
1;
0:
02
11
1-
0<
#450
1#
1<
b1010 @
#500
0"
b1100001010 !
0#
0;
12
0<
#550
1#
1<
b1011 >
1,
1+
0*
1)
0(
0'
0&
0%
